adorable/__init__.py
adorable/_color_space.py
adorable/ansi.py
adorable/color.py
adorable/common.py
adorable/palettes.py
adorable/py.typed
adorable/style.py
adorable2-0.1.1.dist-info/LICENSE.txt
adorable2-0.1.1.dist-info/METADATA
adorable2-0.1.1.dist-info/WHEEL
adorable2-0.1.1.dist-info/RECORD
