Metadata-Version: 2.3
Name: adorable2
Version: 0.1.1
Summary: Make text adorable.
License: MIT License
Author: Jonas da Silva
Author-email: phoenixr41414141@gmail.com
Requires-Python: >=3.13
Classifier: License :: Other/Proprietary License
Classifier: Programming Language :: Python :: 3
Classifier: Programming Language :: Python :: 3.13
Provides-Extra: dev
Provides-Extra: docs
Requires-Dist: Sphinx (==8.2.3) ; extra == "docs"
Requires-Dist: attrs (>=25.3.0,<26.0.0)
Requires-Dist: furo (==2024.8.6) ; extra == "docs"
Requires-Dist: isort (==6.0.1) ; extra == "dev"
Requires-Dist: mypy (==1.16.1) ; extra == "dev"
Requires-Dist: myst-parser (==4.0.1) ; extra == "docs"
Requires-Dist: nox (==2025.5.1) ; extra == "dev"
Requires-Dist: pytest (==8.4.1) ; extra == "dev"
Requires-Dist: ruff (==0.12.0) ; extra == "dev"
Requires-Dist: sphinx-autodoc2 (==0.5.0) ; extra == "docs"
Project-URL: Bug Tracker, https://github.com/phoenixr-codes/adorable2/issues
Project-URL: Documentation, https://phoenixr-codes.github.io/adorable2
Project-URL: Repository, https://github.com/phoenixr-codes/adorable2
